LICENSE
README.md
setup.py
Topsis_Rijul_102103399/__init__.py
Topsis_Rijul_102103399/__main__.py
Topsis_Rijul_102103399.egg-info/PKG-INFO
Topsis_Rijul_102103399.egg-info/SOURCES.txt
Topsis_Rijul_102103399.egg-info/dependency_links.txt
Topsis_Rijul_102103399.egg-info/requires.txt
Topsis_Rijul_102103399.egg-info/top_level.txt