Metadata-Version: 2.1
Name: Topsis_Rijul_102103399
Version: 1.2.0
Summary: Automatic topsis for decision making
Author: Rijul
Author-email: rjain_be21@thapar.edu
Keywords: command-line,topsis-python,TOPSIS
Classifier: Programming Language :: Python :: 3
Classifier: License :: OSI Approved :: MIT License
Classifier: Operating System :: OS Independent
Requires-Python: >=3.6
License-File: LICENSE
Requires-Dist: numpy
Requires-Dist: pandas
